{
  "missingSince": {
    "https://www.autotrader.co.uk/car-details/202510036872708": {
      "count": 2,
      "firstMissed": "2026-04-08"
    },
    "https://www.autotrader.co.uk/car-details/202603140705900": {
      "count": 1,
      "firstMissed": "2026-04-10"
    },
    "https://www.autotrader.co.uk/car-details/202604071346089": {
      "count": 2,
      "firstMissed": "2026-04-10"
    },
    "https://www.pistonheads.com/buy/listing/20217694": {
      "count": 2,
      "firstMissed": "2026-04-10"
    },
    "https://www.carandclassic.com/car/C2027801": {
      "count": 2,
      "firstMissed": "2026-04-11"
    },
    "https://www.autotrader.co.uk/car-details/202603130681944": {
      "count": 1,
      "firstMissed": "2026-04-12"
    }
  }
}
