{
  "missingSince": {
    "https://www.autotrader.co.uk/car-details/202511177936638": {
      "count": 2,
      "firstMissed": "2026-04-12"
    },
    "https://www.autotrader.co.uk/car-details/202602169955344": {
      "count": 2,
      "firstMissed": "2026-04-12"
    },
    "https://www.autotrader.co.uk/car-details/202603170777347": {
      "count": 2,
      "firstMissed": "2026-04-12"
    },
    "https://www.autotrader.co.uk/car-details/202603150712403": {
      "count": 2,
      "firstMissed": "2026-04-12"
    },
    "https://www.autotrader.co.uk/car-details/202602200089353": {
      "count": 2,
      "firstMissed": "2026-04-12"
    },
    "https://www.autotrader.co.uk/car-details/202603120627429": {
      "count": 2,
      "firstMissed": "2026-04-12"
    },
    "https://www.autotrader.co.uk/car-details/202601159171868": {
      "count": 2,
      "firstMissed": "2026-04-12"
    },
    "https://www.autotrader.co.uk/car-details/202601259415227": {
      "count": 2,
      "firstMissed": "2026-04-12"
    },
    "https://www.pistonheads.com/buy/listing/20157740": {
      "count": 2,
      "firstMissed": "2026-04-13"
    },
    "https://www.pistonheads.com/buy/listing/19986690": {
      "count": 2,
      "firstMissed": "2026-04-13"
    },
    "https://www.pistonheads.com/buy/listing/19972794": {
      "count": 2,
      "firstMissed": "2026-04-13"
    },
    "https://www.pistonheads.com/buy/listing/20039774": {
      "count": 2,
      "firstMissed": "2026-04-13"
    },
    "https://www.pistonheads.com/buy/listing/20043851": {
      "count": 2,
      "firstMissed": "2026-04-13"
    },
    "https://www.pistonheads.com/buy/listing/20227476": {
      "count": 2,
      "firstMissed": "2026-04-13"
    },
    "https://www.autotrader.co.uk/car-details/202509126272066": {
      "count": 1,
      "firstMissed": "2026-04-14"
    },
    "https://www.autotrader.co.uk/car-details/202603230928710": {
      "count": 1,
      "firstMissed": "2026-04-14"
    },
    "https://www.pistonheads.com/buy/listing/20027055": {
      "count": 1,
      "firstMissed": "2026-04-14"
    },
    "https://www.pistonheads.com/buy/listing/19814768": {
      "count": 1,
      "firstMissed": "2026-04-14"
    },
    "https://www.autotrader.co.uk/car-details/202602109825172": {
      "count": 1,
      "firstMissed": "2026-04-14"
    },
    "https://www.autotrader.co.uk/car-details/202603210898374": {
      "count": 1,
      "firstMissed": "2026-04-14"
    },
    "https://www.autotrader.co.uk/car-details/202603301130140": {
      "count": 1,
      "firstMissed": "2026-04-14"
    },
    "https://www.carandclassic.com/car/C2040475": {
      "count": 1,
      "firstMissed": "2026-04-14"
    },
    "https://www.autotrader.co.uk/car-details/202604021248965": {
      "count": 1,
      "firstMissed": "2026-04-14"
    },
    "https://www.pistonheads.com/buy/listing/20233031": {
      "count": 1,
      "firstMissed": "2026-04-14"
    },
    "https://www.pistonheads.com/buy/listing/20245299": {
      "count": 1,
      "firstMissed": "2026-04-14"
    },
    "https://www.pistonheads.com/buy/listing/20243890": {
      "count": 1,
      "firstMissed": "2026-04-14"
    },
    "https://www.pistonheads.com/buy/listing/20053012": {
      "count": 1,
      "firstMissed": "2026-04-14"
    },
    "https://www.pistonheads.com/buy/listing/20048038": {
      "count": 1,
      "firstMissed": "2026-04-14"
    },
    "https://www.autotrader.co.uk/car-details/202604111473096": {
      "count": 1,
      "firstMissed": "2026-04-14"
    },
    "https://www.autotrader.co.uk/car-details/202604011212387": {
      "count": 1,
      "firstMissed": "2026-04-14"
    }
  }
}
