{
  "missingSince": {
    "https://www.pistonheads.com/buy/listing/19468745": {
      "count": 2,
      "firstMissed": "2026-03-13"
    },
    "https://www.pistonheads.com/buy/listing/19946605": {
      "count": 2,
      "firstMissed": "2026-03-13"
    },
    "https://www.pistonheads.com/buy/listing/19905678": {
      "count": 2,
      "firstMissed": "2026-03-13"
    },
    "https://www.pistonheads.com/buy/listing/19731509": {
      "count": 2,
      "firstMissed": "2026-03-13"
    },
    "https://www.carandclassic.com/car/C2015696": {
      "count": 2,
      "firstMissed": "2026-03-13"
    },
    "https://www.carandclassic.com/car/C1972100": {
      "count": 2,
      "firstMissed": "2026-03-13"
    },
    "https://www.carandclassic.com/car/C1975100": {
      "count": 1,
      "firstMissed": "2026-03-14"
    },
    "https://www.pistonheads.com/buy/listing/19996780": {
      "count": 1,
      "firstMissed": "2026-03-14"
    }
  }
}
