{
  "missingSince": {
    "https://www.autotrader.co.uk/car-details/202511107777893": {
      "count": 2,
      "firstMissed": "2026-04-27"
    },
    "https://www.autotrader.co.uk/car-details/202509256635745": {
      "count": 2,
      "firstMissed": "2026-04-27"
    },
    "https://www.autotrader.co.uk/car-details/202510097026496": {
      "count": 2,
      "firstMissed": "2026-04-27"
    },
    "https://www.autotrader.co.uk/car-details/202604141543037": {
      "count": 2,
      "firstMissed": "2026-04-27"
    },
    "https://www.pistonheads.com/buy/listing/20026393": {
      "count": 1,
      "firstMissed": "2026-05-02"
    },
    "https://www.autotrader.co.uk/car-details/202603160738872": {
      "count": 1,
      "firstMissed": "2026-05-02"
    },
    "https://www.autotrader.co.uk/car-details/202604181656222": {
      "count": 1,
      "firstMissed": "2026-05-02"
    }
  }
}
